src/__init__.py
src/__version__.py
src/cli.py
src/exceptions.py
src/log.py
src/clients/__init__.py
src/clients/device_test_client.py
src/clients/e2e_token_client.py
src/clients/hardware_manager_client.py
src/command_impls/__init__.py
src/command_impls/cancel_impl.py
src/command_impls/get_plan_impl.py
src/command_impls/get_run_plan_summary_impl.py
src/command_impls/release_device_impl.py
src/command_impls/run_eleven_calibration_impl.py
src/command_impls/run_eyepatch_calibration_impl.py
src/command_impls/run_impl.py
src/command_impls/status_impl.py
tests/__init__.py
tests/conftest.py
tests/test_cli.py
tests/test_command_impls.py
tests/test_exceptions.py
tests/clients/__init__.py
tests/clients/test_device_test_client.py
tests/clients/test_e2e_token_client.py
tests/clients/test_hardware_manager_client.py
ntscli_client-3.1.4.dist-info/METADATA
ntscli_client-3.1.4.dist-info/WHEEL
ntscli_client-3.1.4.dist-info/entry_points.txt
ntscli_client-3.1.4.dist-info/top_level.txt
ntscli_client-3.1.4.dist-info/RECORD
