Metadata-Version: 2.4
Name: ntscli-client
Version: 3.1.4
Summary: NTS-CLI - The Netflix Test Studio Command Line Interface (NTS-CLI) offers an alternative method for testing your Netflix application.
Home-page: https://docs.nrd.netflix.com/docs/nrdp/cert/ntscli/
Author: eco-eai@netflix.com
Requires-Python: >=3.8
Requires-Dist: click
Requires-Dist: click-completion
Requires-Dist: click-log
Requires-Dist: colorama
Requires-Dist: dataclasses; python_version < "3.8"
Requires-Dist: furl
Requires-Dist: requests
Requires-Dist: requests_toolbelt
Requires-Dist: uri
Requires-Dist: xdg
Provides-Extra: internal
Requires-Dist: pytest>=7.0; extra == "internal"
Requires-Dist: pytest-cov>=4.0; extra == "internal"
Requires-Dist: pytest-mock>=3.10; extra == "internal"
Requires-Dist: mock; extra == "internal"
Requires-Dist: metatron; extra == "internal"
Requires-Dist: behave; extra == "internal"
Requires-Dist: flake8; extra == "internal"
Requires-Dist: mypy; extra == "internal"
Requires-Dist: pyinstaller; extra == "internal"
Requires-Dist: semver; extra == "internal"
Requires-Dist: tox; extra == "internal"
Dynamic: author
Dynamic: description
Dynamic: description-content-type
Dynamic: home-page
Dynamic: provides-extra
Dynamic: requires-dist
Dynamic: requires-python
Dynamic: summary
